arc_lib/__init__.py
arc_lib/text.py
arc_lib_arodroz-0.0.3.dist-info/LICENSE
arc_lib_arodroz-0.0.3.dist-info/METADATA
arc_lib_arodroz-0.0.3.dist-info/WHEEL
arc_lib_arodroz-0.0.3.dist-info/top_level.txt
arc_lib_arodroz-0.0.3.dist-info/RECORD
