Metadata-Version: 2.1
Name: arc-lib-arodroz
Version: 0.0.3
Summary: Text tools
Home-page: https://github.com/arodroz/arc_lib
Author: Antonio Rodriguez
Author-email: arodroz@icloud.com
License: UNKNOWN
Project-URL: Bug Tracker, https://github.com/arodroz/arc_lib/issues
Platform: UNKNOWN
Classifier: Programming Language :: Python :: 3
Classifier: License :: OSI Approved :: MIT License
Classifier: Operating System :: OS Independent
Requires-Python: >=3.6
License-File: LICENSE
